setux/main/__init__.py
setux-0.2511.0.dist-info/METADATA
setux-0.2511.0.dist-info/WHEEL
setux-0.2511.0.dist-info/top_level.txt
setux-0.2511.0.dist-info/RECORD
