Metadata-Version: 2.2
Name: setux
Version: 0.2511.0
Summary: System deployment
Author-email: Louis RIVIERE <louis@riviere.xyz>
Maintainer-email: Louis RIVIERE <louis@riviere.xyz>
License: MIT
Project-URL: Homepage, https://pypi.org/project/setux
Project-URL: pypi, https://pypi.org/project/setux
Project-URL: repository, https://framagit.org/louis-riviere-xyz/setux
Project-URL: Documentation, https://setux.readthedocs.io
Keywords: utility
Classifier: Development Status :: 3 - Alpha
Classifier: License :: OSI Approved :: MIT License
Classifier: Programming Language :: Python :: 3
Classifier: Operating System :: POSIX :: Linux
Classifier: Environment :: Console
Classifier: Intended Audience :: Developers
Classifier: Intended Audience :: Information Technology
Classifier: Intended Audience :: System Administrators
Classifier: Topic :: System :: Installation/Setup
Classifier: Topic :: System :: Systems Administration
Classifier: Topic :: Utilities
Requires-Dist: setux_core>=0.2507.6
Requires-Dist: setux_actions>=0.2507.6
Requires-Dist: setux_distros>=0.2507.4
Requires-Dist: setux_logger>=0.2343.0
Requires-Dist: setux_managers>=0.2507.3
Requires-Dist: setux_mappings>=0.2343.0
Requires-Dist: setux_modules>=0.2506.0
Requires-Dist: setux_targets>=0.2511.0
